golem_cloud/__init__.py
golem_cloud/durability.py
golem_cloud/host.py
golem_cloud/transaction.py
golem_cloud-0.2.0.dist-info/licenses/LICENSE
golem_cloud-0.2.0.dist-info/WHEEL
golem_cloud-0.2.0.dist-info/METADATA
golem_cloud-0.2.0.dist-info/RECORD
