Metadata-Version: 2.4
Name: golem-cloud
Version: 0.2.0
Summary: A library that helps with writing Golem components in Python 
License-Expression: Apache-2.0
License-File: LICENSE
Classifier: License :: OSI Approved :: Apache Software License
Classifier: Environment :: WebAssembly :: WASI
Classifier: Typing :: Typed
Requires-Python: >=3.12
Project-URL: Documentation, https://github.com/golemcloud/golem-py
Project-URL: Homepage, https://github.com/golemcloud/golem-py
Project-URL: Repository, https://github.com/golemcloud/golem-py
